MANIFEST.in
README.md
setup.py
neuro_athelets/__init__.py
neuro_athelets/analytics_engine.py
neuro_athelets/eeg_utilities.py
neuro_athelets/file_utilities.py
neuro_athelets/process_wfft.py
neuro_athelets/read_csv.py
neuro_athelets/read_csv_anova.py
neuro_athelets/read_csv_get_individual.py
neuro_athelets/read_csv_wilcox.py
neuro_athelets/read_linr.py
neuro_athelets/txt_utilities.py
neuro_athelets.egg-info/PKG-INFO
neuro_athelets.egg-info/SOURCES.txt
neuro_athelets.egg-info/dependency_links.txt
neuro_athelets.egg-info/not-zip-safe
neuro_athelets.egg-info/requires.txt
neuro_athelets.egg-info/top_level.txt