Metadata-Version: 1.1
Name: neuro-athelets
Version: 0.11
Summary: python ml library for neuro eeg data
Home-page: http://github.com/leolincoln/neuro_athelets
Author: Liu Liu
Author-email: leoliu@u.northwestern.edu
License: MIT
Platform: UNKNOWN
Classifier: Development Status :: 3 - Alpha
Classifier: License :: OSI Approved :: MIT License
Classifier: Programming Language :: Python :: 2.7
Classifier: Topic :: Scientific/Engineering :: Information Analysis
Classifier: Topic :: Scientific/Engineering :: Medical Science Apps.
Classifier: Topic :: Scientific/Engineering :: Visualization
